steem_verifier-1.0.0.dist-info/METADATA
steem_verifier-1.0.0.dist-info/RECORD
steem_verifier-1.0.0.dist-info/WHEEL
steem_verifier-1.0.0.dist-info/entry_points.txt
steem_verifier-1.0.0.dist-info/top_level.txt
verifier/__init__.py
verifier/__main__.py
verifier/cli.py
verifier/verifier.py
