Metadata-Version: 2.1
Name: steem-verifier
Version: 1.0.0
Summary: Easy verification of Steem transaction signatures.
Home-page: https://github.com/hernandev/verifier
Author: Diego Hernandes
Author-email: diego@hernandev.com
License: MIT
Keywords: steem,steemit,signature,transaction
Platform: UNKNOWN
Classifier: Intended Audience :: Developers
Classifier: License :: OSI Approved :: MIT License
Classifier: Natural Language :: English
Classifier: Programming Language :: Python :: 3
Classifier: Programming Language :: Python :: 3.5
Classifier: Topic :: Software Development :: Libraries
Classifier: Topic :: Software Development :: Libraries :: Python Modules
Classifier: Development Status :: 4 - Beta
Provides-Extra: dev
Provides-Extra: build
Requires-Dist: steem
Provides-Extra: build
Requires-Dist: twine; extra == 'build'
Requires-Dist: wheel; extra == 'build'
Requires-Dist: setuptools; extra == 'build'
Provides-Extra: dev
Requires-Dist: twine; extra == 'dev'
Requires-Dist: wheel; extra == 'dev'
Requires-Dist: setuptools; extra == 'dev'
